sudoku_lhs-0.1.1.dist-info/RECORD
sudoku_lhs-0.1.1.dist-info/top_level.txt
sudoku_lhs-0.1.1.dist-info/METADATA
sudoku_lhs-0.1.1.dist-info/DESCRIPTION.rst
sudoku_lhs-0.1.1.dist-info/metadata.json
sudoku_lhs-0.1.1.dist-info/WHEEL
sudoku_lhs-0.1.1.dist-info/zip-safe
sudoku_lhs-0.1.1.data/data/CHANGELOG.md
sudoku_lhs-0.1.1.data/data/LICENSE.md
sudoku_lhs-0.1.1.data/data/README.md
sudoku_lhs-0.1.1.data/data/test/sudoku_cor_test.py
sudoku_lhs/sudoku.py
sudoku_lhs/lhs.py
sudoku_lhs/__init__.py
sudoku_lhs/comb.py
