Metadata-Version: 2.0
Name: sudoku-lhs
Version: 0.1.1
Summary: LHS with sudoku constraint
Home-page: https://github.com/Technologicat/sudoku_lhs
Author: Juha Jeronen
Author-email: juha.jeronen@jyu.fi
License: BSD
Keywords: latin-hypercube sudoku numerical sampling-methods numpy
Platform: Linux
Classifier: Development Status :: 4 - Beta
Classifier: Environment :: Console
Classifier: Intended Audience :: Developers
Classifier: Intended Audience :: Science/Research
Classifier: License :: OSI Approved :: BSD License
Classifier: Operating System :: POSIX :: Linux
Classifier: Programming Language :: Python
Classifier: Programming Language :: Python :: 2
Classifier: Programming Language :: Python :: 2.7
Classifier: Programming Language :: Python :: 3
Classifier: Programming Language :: Python :: 3.4
Classifier: Topic :: Scientific/Engineering
Classifier: Topic :: Scientific/Engineering :: Mathematics
Classifier: Topic :: Software Development :: Libraries
Classifier: Topic :: Software Development :: Libraries :: Python Modules
Provides: sudoku_lhs
Requires-Dist: numpy
